theiaphylo/__init__.py
theiaphylo/_version.py
theiaphylo/clean_phylo.R
theiaphylo/gen_cophylo.R
theiaphylo/phyloutils.py
theiaphylo/phylovalidate.py
theiaphylo/lib/StdPath.py
theiaphylo/lib/__init__.py
theiaphylo-0.2.0.dist-info/licenses/LICENSE
theiaphylo-0.2.0.dist-info/METADATA
theiaphylo-0.2.0.dist-info/WHEEL
theiaphylo-0.2.0.dist-info/entry_points.txt
theiaphylo-0.2.0.dist-info/top_level.txt
theiaphylo-0.2.0.dist-info/RECORD
