Metadata-Version: 2.4
Name: theiaphylo
Version: 0.2.0
Summary: A collection of phylogenetic analysis tools for Theiagen platforms
Author-email: Zachary Konkel <zachary.konkel@theiagen.com>
License:                     GNU GENERAL PUBLIC LICENSE
Project-URL: Homepage, https://github.com/theiagen/theiaphylo
Project-URL: Bug Tracker, https://github.com/theiagen/theiaphylo/issues
Classifier: Programming Language :: Python :: 3
Classifier: License :: OSI Approved :: GNU Lesser General Public License v3 or later (LGPLv3+)
Classifier: Operating System :: POSIX :: Linux
Requires-Python: <4,>=3.0
License-File: LICENSE
Requires-Dist: cogent3==2025.7.10a10
Requires-Dist: ete3
Dynamic: license-file
